variantlib/__init__.py
variantlib/api.py
variantlib/cache.py
variantlib/configuration.py
variantlib/constants.py
variantlib/dist_metadata.py
variantlib/errors.py
variantlib/protocols.py
variantlib/pyproject_toml.py
variantlib/utils.py
variantlib/validators.py
variantlib/variants_json.py
variantlib/commands/__init__.py
variantlib/commands/analyze_platform.py
variantlib/commands/analyze_wheel.py
variantlib/commands/generate_index_json.py
variantlib/commands/index_json_utils.py
variantlib/commands/main.py
variantlib/commands/make_variant.py
variantlib/commands/plugin_arguments.py
variantlib/commands/unmake_variant.py
variantlib/commands/config/__init__.py
variantlib/commands/config/list_paths.py
variantlib/commands/config/main.py
variantlib/commands/config/setup.py
variantlib/commands/config/show.py
variantlib/commands/config/variants.dist.toml
variantlib/commands/config/setup_interfaces/__init__.py
variantlib/commands/config/setup_interfaces/console_ui.py
variantlib/commands/config/setup_interfaces/urwid_ui.py
variantlib/commands/plugins/__init__.py
variantlib/commands/plugins/_display_configs.py
variantlib/commands/plugins/get_all_configs.py
variantlib/commands/plugins/get_supported_configs.py
variantlib/commands/plugins/list_plugins.py
variantlib/commands/plugins/main.py
variantlib/models/__init__.py
variantlib/models/base.py
variantlib/models/configuration.py
variantlib/models/metadata.py
variantlib/models/provider.py
variantlib/models/variant.py
variantlib/plugins/__init__.py
variantlib/plugins/loader.py
variantlib/plugins/py_backends.py
variantlib/plugins/py_envs.py
variantlib/resolver/__init__.py
variantlib/resolver/filtering.py
variantlib/resolver/lib.py
variantlib/resolver/sorting.py
variantlib-0.0.1.post1.dist-info/entry_points.txt
variantlib-0.0.1.post1.dist-info/licenses/LICENSE
variantlib-0.0.1.post1.dist-info/WHEEL
variantlib-0.0.1.post1.dist-info/METADATA
variantlib-0.0.1.post1.dist-info/RECORD
