Metadata-Version: 2.4
Name: variantlib
Version: 0.0.1.post1
Summary: A library to provide support for variants
Author-email: Jonathan Dekhtiar <jonathan@dekhtiar.com>, Michał Górny <mgorny@quansight.com>, Michael Sarahan <msarahan@nvidia.com>
Maintainer-email: Jonathan Dekhtiar <jonathan@dekhtiar.com>, Michał Górny <mgorny@quansight.com>, Michael Sarahan <msarahan@nvidia.com>
Requires-Python: >=3.9
License-File: LICENSE
Requires-Dist: importlib-metadata; python_version < '3.10'
Requires-Dist: packaging>=25.0,<26.0
Requires-Dist: platformdirs>=4.3,<5.0
Requires-Dist: tomli; python_version < '3.11'
Requires-Dist: typing-extensions; python_version < '3.11'
Requires-Dist: tomlkit>=0.13,<0.14 ; extra == "cli"
Requires-Dist: tzlocal>=3.0,<6 ; extra == "cli"
Requires-Dist: urwid>=2.6.0,<3 ; extra == "cli"
Requires-Dist: check-manifest ; extra == "dev"
Requires-Dist: pre-commit>=4,<5 ; extra == "dev"
Requires-Dist: ruff>=0.10,<1.0 ; extra == "dev"
Requires-Dist: deepdiff>=8.0,<9.0 ; extra == "test"
Requires-Dist: hypothesis>=6.0.0,<7 ; extra == "test"
Requires-Dist: parameterized>=0.9.0,<0.10 ; extra == "test"
Requires-Dist: pytest>=8.0.0,<9.0.0 ; extra == "test"
Requires-Dist: pytest-cov>=5.0.0,<6.0.0 ; extra == "test"
Requires-Dist: pytest-dotenv>=0.5.0,<1.0.0 ; extra == "test"
Requires-Dist: pytest-env>=1.1.3,<2.0.0 ; extra == "test"
Requires-Dist: pytest-mock>=3.14.0,<4.0.0 ; extra == "test"
Requires-Dist: pytest-runner>=6.0.0,<7.0.0 ; extra == "test"
Requires-Dist: pytest-ordering>=0.6,<1.0.0 ; extra == "test"
Requires-Dist: virtualenv>=20.0.0,<21.0.0 ; extra == "test"
Requires-Dist: tomlkit>=0.13,<0.14 ; extra == "test"
Requires-Dist: uv>=0.7,<0.8 ; extra == "test"
Provides-Extra: cli
Provides-Extra: dev
Provides-Extra: test
